StructReader/Struct_Reader.py
StructReader/__init__.py
structreader-1.0.33.dist-info/licenses/LICENSE
structreader-1.0.33.dist-info/METADATA
structreader-1.0.33.dist-info/WHEEL
structreader-1.0.33.dist-info/top_level.txt
structreader-1.0.33.dist-info/RECORD
